langgraph_guard/__init__.py
langgraph_guard/bootstrap.py
langgraph_guard/guard_callback_blocks_only.py
langgraph_guard-0.1.4.dist-info/METADATA
langgraph_guard-0.1.4.dist-info/WHEEL
langgraph_guard-0.1.4.dist-info/top_level.txt
langgraph_guard-0.1.4.dist-info/RECORD
