Metadata-Version: 2.4
Name: langgraph-guard
Version: 0.1.4
Summary: This package is required for integrating your Langchain based Agentic Application to Aryaka's AISecure Guard Service.
Author-email: Aryaka Networks <sid.padmanabhuni@aryaka.com>
License-Expression: Apache-2.0
Requires-Python: >=3.9
Requires-Dist: httpx>=0.24
Requires-Dist: pydantic>=2.0
Requires-Dist: langchain-core>=0.2.0
